LoggingSelenium/LogHTML.py
LoggingSelenium/__init__.py
LoggingSelenium/ttt.py
selenium_logging-0.0.6.dist-info/METADATA
selenium_logging-0.0.6.dist-info/WHEEL
selenium_logging-0.0.6.dist-info/top_level.txt
selenium_logging-0.0.6.dist-info/RECORD
